helloadd/__init__.py
helloadd/project.py
helloadd-1.0.dist-info/METADATA
helloadd-1.0.dist-info/WHEEL
helloadd-1.0.dist-info/top_level.txt
helloadd-1.0.dist-info/RECORD
