Metadata-Version: 2.1
Name: helloadd
Version: 1.0
Summary: prints addtional of two number
